LICENSE.md
README.md
setup.py
src/qilib/__init__.py
src/qilib/version.py
src/qilib.egg-info/PKG-INFO
src/qilib.egg-info/SOURCES.txt
src/qilib.egg-info/dependency_links.txt
src/qilib.egg-info/requires.txt
src/qilib.egg-info/top_level.txt
src/qilib/configuration_helper/__init__.py
src/qilib/configuration_helper/configuration_helper.py
src/qilib/configuration_helper/exceptions.py
src/qilib/configuration_helper/instrument_adapter.py
src/qilib/configuration_helper/instrument_adapter_factory.py
src/qilib/configuration_helper/instrument_configuration.py
src/qilib/configuration_helper/instrument_configuration_set.py
src/qilib/configuration_helper/instrument_configuration_visitor.py
src/qilib/configuration_helper/serial_port_resolver.py
src/qilib/configuration_helper/visitor.py
src/qilib/configuration_helper/adapters/__init__.py
src/qilib/configuration_helper/adapters/ami430_instrument_adapter.py
src/qilib/configuration_helper/adapters/common_instrument_adapter.py
src/qilib/configuration_helper/adapters/d5a_instrument_adapter.py
src/qilib/configuration_helper/adapters/f1d_instrument_adapter.py
src/qilib/configuration_helper/adapters/keithley_dmm6500_adapter.py
src/qilib/configuration_helper/adapters/keysight_e8267d_instrument_adapter.py
src/qilib/configuration_helper/adapters/m2j_instrument_adapter.py
src/qilib/configuration_helper/adapters/m4i_instrument_adapter.py
src/qilib/configuration_helper/adapters/read_only_configuration_instrument_adapter.py
src/qilib/configuration_helper/adapters/s5i_instrument_adapter.py
src/qilib/configuration_helper/adapters/spi_module_instrument_adapter.py
src/qilib/configuration_helper/adapters/spi_rack_instrument_adapter.py
src/qilib/data_set/__init__.py
src/qilib/data_set/data_array.py
src/qilib/data_set/data_set.py
src/qilib/data_set/data_set_io_reader.py
src/qilib/data_set/data_set_io_writer.py
src/qilib/data_set/memory_data_set_io_factory.py
src/qilib/data_set/memory_data_set_io_reader.py
src/qilib/data_set/memory_data_set_io_writer.py
src/qilib/data_set/mongo_data_set_io.py
src/qilib/data_set/mongo_data_set_io_reader.py
src/qilib/data_set/mongo_data_set_io_writer.py
