Metadata-Version: 2.1
Name: qilib
Version: 0.3.12
Summary: Quantum Library for the Quantum Inspire platform
Home-page: https://qutech.nl
Author: QuantumInspire
Author-email: support@quantum-inspire.com
License: MIT
Platform: UNKNOWN
Classifier: Development Status :: 3 - Alpha
Classifier: Programming Language :: Python :: 3
Classifier: Programming Language :: Python :: 3.7
Classifier: Programming Language :: Python :: 3.8
Classifier: Programming Language :: Python :: 3.9
Classifier: Programming Language :: Python :: 3.10
Classifier: Programming Language :: Python :: 3.11
Requires-Python: >=3.7
Provides-Extra: dev
License-File: LICENSE.md
